Metadata-Version: 2.1
Name: object-detection-tf
Version: 0.1.2
Summary: A Thin Wrapper around Tensorflow Object Detection API for Easy Installation and Use
Author: Reza Mohebbian
Author-email: reza.mohebbian@procore.com
License: Apache License 2.0
Classifier: Programming Language :: Python :: 3.7
Classifier: Topic :: Scientific/Engineering :: Artificial Intelligence
Classifier: Intended Audience :: Developers
Classifier: Intended Audience :: Science/Research
Requires-Python: >=3.7, <3.8
License-File: LICENSE
Requires-Dist: setuptools (>=41.0.0)
Requires-Dist: cython
Requires-Dist: contextlib2
Requires-Dist: pillow
Requires-Dist: lxml
Requires-Dist: pycocotools-fix
Requires-Dist: jupyter
Requires-Dist: matplotlib
Provides-Extra: tf
Requires-Dist: tensorflow (<2.0) ; extra == 'tf'
Provides-Extra: tf-gpu
Requires-Dist: tensorflow-gpu (<2.0) ; extra == 'tf-gpu'
